silver_flutterwave/__init__.py
silver_flutterwave/admin.py
silver_flutterwave/apps.py
silver_flutterwave/models.py
silver_flutterwave/payment_processors.py
silver_flutterwave/paypal_client.py
silver_flutterwave/tests.py
silver_flutterwave/views.py
silver_flutterwave-2.0.2.dist-info/LICENSE.txt
silver_flutterwave-2.0.2.dist-info/METADATA
silver_flutterwave-2.0.2.dist-info/WHEEL
silver_flutterwave-2.0.2.dist-info/top_level.txt
silver_flutterwave-2.0.2.dist-info/RECORD
