Metadata-Version: 2.1
Name: silver-flutterwave
Version: 2.0.2
Summary: Stripe pay
Home-page: 
Author: Idah
License-File: LICENSE.txt
